tests/__init__.py
tests/test_fragment.py
tests/test_fragment_query.py
tests/test_fragment_select.py
tests/test_integrational.py
tests/test_parser.py
tests/test_query_tables.py
tests/test_selectors.py
tests/test_table_reflow.py
tests/test_wikipedia_ql.py
wikipedia_ql/__init__.py
wikipedia_ql/fragment.py
wikipedia_ql/media_wiki.py
wikipedia_ql/parser.py
wikipedia_ql/run.py
wikipedia_ql/selectors.py
wikipedia_ql/tables.py
wikipedia_ql/wikipedia_ql.lark
wikipedia_ql-0.0.6.data/scripts/wikipedia_ql
wikipedia_ql-0.0.6.dist-info/LICENSE
wikipedia_ql-0.0.6.dist-info/METADATA
wikipedia_ql-0.0.6.dist-info/WHEEL
wikipedia_ql-0.0.6.dist-info/top_level.txt
wikipedia_ql-0.0.6.dist-info/RECORD
