Metadata-Version: 2.1
Name: wikipedia-ql
Version: 0.0.6
Summary: Query Language for Wikipedia
Home-page: https://github.com/zverok/wikipedia_ql
Author: Victor Shepelev
Author-email: zverok.offline@gmail.com
License: UNKNOWN
Platform: UNKNOWN
Classifier: Development Status :: 3 - Alpha
Classifier: Intended Audience :: Developers
Classifier: Intended Audience :: Education
Classifier: Intended Audience :: Science/Research
Classifier: License :: OSI Approved :: MIT License
Classifier: Programming Language :: Python :: 3.7
Classifier: Programming Language :: Python :: 3.8
Classifier: Programming Language :: Python :: 3.9
Classifier: Operating System :: OS Independent
Classifier: Topic :: Scientific/Engineering :: Information Analysis
Requires-Python: >=3.7
Requires-Dist: requests
Requires-Dist: lark
Requires-Dist: soupsieve (>=2.3.1)
Requires-Dist: bs4
Requires-Dist: nltk
Requires-Dist: pyaml
